pakala/__init__.py
pakala/analyzer.py
pakala/claripy_sha3.py
pakala/cli.py
pakala/env.py
pakala/memory.py
pakala/recursive_analyzer.py
pakala/sm.py
pakala/state.py
pakala/summary.py
pakala/test_analyzer.py
pakala/test_claripy_sha3.py
pakala/test_env.py
pakala/test_memory.py
pakala/test_recursive_analyzer.py
pakala/test_sm.py
pakala/test_state.py
pakala/utils.py
solidity_tests/__init__.py
solidity_tests/test_solidity.py
pakala-1.1.10.dist-info/LICENSE.txt
pakala-1.1.10.dist-info/METADATA
pakala-1.1.10.dist-info/WHEEL
pakala-1.1.10.dist-info/entry_points.txt
pakala-1.1.10.dist-info/top_level.txt
pakala-1.1.10.dist-info/RECORD
