Metadata-Version: 2.1
Name: pakala
Version: 1.1.10
Summary: An EVM symbolic execution tool and vulnerability scanner
Home-page: https://github.com/palkeo/pakala
Author: palkeo
Author-email: ethereum@palkeo.com
License: UNKNOWN
Keywords: ethereum evm symbolic execution vulnerability scanner
Platform: UNKNOWN
Classifier: Development Status :: 4 - Beta
Classifier: Intended Audience :: Developers
Classifier: License :: OSI Approved :: GNU General Public License v3 (GPLv3)
Classifier: Programming Language :: Python :: 3
Requires-Dist: py-evm (==0.3.0a12)
Requires-Dist: claripy (==8.19.7.25)
Requires-Dist: mock
Requires-Dist: web3 (==5.3.0)
Requires-Dist: coloredlogs (==10.0)
Requires-Dist: eth-utils (==1.8.1)
